Lya_zelda_II/__init__.py
Lya_zelda_II/funcs.py
Lya_zelda_II/DATA/List_of_DATA_files
Lya_zelda_II/DATA/List_of_DATA_files_II
Lya_zelda_II/DATA/nn_INFLOWS_N_2500000_Npix_1000_Dl_-18.5_18.5_Dc_True_nor_False_sca_True_256_256_256_256_256_it_1.sav
Lya_zelda_II/DATA/nn_OUTFLOW_N_2500000_Npix_1000_Dl_-18.5_18.5_Dc_True_nor_False_sca_True_256_256_256_256_256_it_1.sav
Lya_zelda_II/DATA/MODELS_ZELDA_II/MODELS_NoIGM/data_PCA_Nbins_600_Dmin_-12.0_Dmax_12.0_Dcore_True_Ntrain_50000.npy
Lya_zelda_II/DATA/MODELS_ZELDA_II/MODELS_NoIGM/data_Uncertainty_corrections_FACTOR_COMPUTATION_Dl.npy
Lya_zelda_II/DATA/MODELS_ZELDA_II/MODELS_NoIGM/data_Uncertainty_corrections_FACTOR_COMPUTATION_f1A.npy
Lya_zelda_II/DATA/MODELS_ZELDA_II/MODELS_NoIGM/data_Uncertainty_corrections_FACTOR_COMPUTATION_f2A.npy
Lya_zelda_II/DATA/MODELS_ZELDA_II/MODELS_NoIGM/data_Uncertainty_corrections_FACTOR_COMPUTATION_f4A.npy
Lya_zelda_II/DATA/MODELS_ZELDA_II/MODELS_NoIGM/data_Uncertainty_corrections_FACTOR_COMPUTATION_logE.npy
Lya_zelda_II/DATA/MODELS_ZELDA_II/MODELS_NoIGM/data_Uncertainty_corrections_FACTOR_COMPUTATION_logN.npy
Lya_zelda_II/DATA/MODELS_ZELDA_II/MODELS_NoIGM/data_Uncertainty_corrections_FACTOR_COMPUTATION_logV.npy
Lya_zelda_II/DATA/MODELS_ZELDA_II/MODELS_NoIGM/data_Uncertainty_corrections_FACTOR_COMPUTATION_logW.npy
Lya_zelda_II/DATA/MODELS_ZELDA_II/MODELS_NoIGM/data_Uncertainty_corrections_FACTOR_COMPUTATION_logt.npy
Lya_zelda_II/DATA/MODELS_ZELDA_II/MODELS_NoIGM/nn_OUTFLOW_Npca_100_N_1500000_103_53_25_prop_f10A_it_0.sav
Lya_zelda_II/DATA/MODELS_ZELDA_II/MODELS_NoIGM/nn_OUTFLOW_Npca_100_N_1500000_103_53_25_prop_f1A_it_0.sav
Lya_zelda_II/DATA/MODELS_ZELDA_II/MODELS_NoIGM/nn_OUTFLOW_Npca_100_N_1500000_103_53_25_prop_f2A_it_0.sav
Lya_zelda_II/DATA/MODELS_ZELDA_II/MODELS_NoIGM/nn_OUTFLOW_Npca_100_N_1500000_103_53_25_prop_f3A_it_0.sav
Lya_zelda_II/DATA/MODELS_ZELDA_II/MODELS_NoIGM/nn_OUTFLOW_Npca_100_N_1500000_103_53_25_prop_f4A_it_0.sav
lya_zelda_ii-1.0.6.dist-info/licenses/LICENSE
lya_zelda_ii-1.0.6.dist-info/METADATA
lya_zelda_ii-1.0.6.dist-info/WHEEL
lya_zelda_ii-1.0.6.dist-info/top_level.txt
lya_zelda_ii-1.0.6.dist-info/RECORD
