Metadata-Version: 2.4
Name: Lya_zelda_II
Version: 1.0.6
Summary: Lyman alpha for everyone
Author-email: Siddhartha Gurung Lopez <gurung.lopez@gmail.com>
Project-URL: Homepage, https://github.com/sidgl/zELDA_II
Project-URL: Issues, https://github.com/sidgl/zELDA_II
Classifier: Programming Language :: Python :: 3
Classifier: License :: OSI Approved :: MIT License
Classifier: Operating System :: OS Independent
Requires-Python: >=3.12
License-File: LICENSE
Requires-Dist: scikit-learn==1.5
Requires-Dist: pyswarms==1.3.0
Requires-Dist: emcee==3.1.2
Requires-Dist: numpy<2.0.0
Dynamic: license-file
